flytekitplugins_vscode-1.10.1-py3.12-nspkg.pth
flytekitplugins/vscode/__init__.py
flytekitplugins/vscode/constants.py
flytekitplugins/vscode/decorator.py
flytekitplugins_vscode-1.10.1.dist-info/METADATA
flytekitplugins_vscode-1.10.1.dist-info/WHEEL
flytekitplugins_vscode-1.10.1.dist-info/entry_points.txt
flytekitplugins_vscode-1.10.1.dist-info/namespace_packages.txt
flytekitplugins_vscode-1.10.1.dist-info/top_level.txt
flytekitplugins_vscode-1.10.1.dist-info/RECORD
